OpenPyxlLibrary
