Metadata-Version: 1.0
Name: robotframework-openpyxllib
Version: 0.7
Summary: Robotframework library for excel xlsx file format
Home-page: https://github.com/vallikkv/robotframework-openpyxllib
Author: Vallinayagam.K
Author-email: valli.python@gmail.com
License: UNKNOWN
Platform: UNKNOWN
